[{"code":"BG","name":"Bahr el Gazel"},{"code":"BA","name":"Batha Region"},{"code":"BO","name":"Borkou"},{"code":"EN","name":"Ennedi Region"},{"code":"EE","name":"Ennedi-Est"},{"code":"EO","name":"Ennedi-Ouest"},{"code":"GR","name":"Guéra Region"},{"code":"HL","name":"Hadjer-Lamis"},{"code":"KA","name":"Kanem Region"},{"code":"LC","name":"Lac Region"},{"code":"LO","name":"Logone Occidental Region"},{"code":"LR","name":"Logone Oriental Region"},{"code":"MA","name":"Mandoul Region"},{"code":"ME","name":"Mayo-Kebbi Est Region"},{"code":"MO","name":"Mayo-Kebbi Ouest Region"},{"code":"MC","name":"Moyen-Chari Region"},{"code":"ND","name":"N'Djamena"},{"code":"OD","name":"Ouaddaï Region"},{"code":"SA","name":"Salamat Region"},{"code":"SI","name":"Sila Region"},{"code":"TA","name":"Tandjilé Region"},{"code":"TI","name":"Tibesti Region"},{"code":"WF","name":"Wadi Fira Region"}]